simple_rest_call.py
simple_rest_call-0.1a9.dist-info/LICENSE
simple_rest_call-0.1a9.dist-info/METADATA
simple_rest_call-0.1a9.dist-info/WHEEL
simple_rest_call-0.1a9.dist-info/top_level.txt
simple_rest_call-0.1a9.dist-info/RECORD
