Metadata-Version: 2.1
Name: simple-rest-call
Version: 0.1a9
Summary: Simple RESTful Call
Home-page: https://github.com/DataBooster/PyWebApi
Author: Abel Cheng
Author-email: abelcys@gmail.com
License: MIT
Keywords: RESTful,Request,JSON,WebAPI,DateTime,Windows,Authentication
Platform: any
Requires-Python: >=3.6
Requires-Dist: requests-negotiate-sspi
Requires-Dist: jsonpickle
Requires-Dist: python-dateutil
